{"is_source_file": true, "file_id": 3, "git_revision": "493ac0071a7a0203ac6ccf270c4300e8451a4f80", "state": 2, "description": "", "external_files": [], "external_methods": [], "published": [], "classes": [], "methods": [], "calls": [], "search-terms": [], "ctags": [], "hash": null, "format-version": 4, "code-base-name": "inventory_backend_api", "filename": "inventory_backend_api/src/api/__init__.py", "knowledge_revision": 6, "revision_history": [{"6": "493ac0071a7a0203ac6ccf270c4300e8451a4f80"}]}